MANIFEST.in
README.rst
setup.py
aws_helper/__init__.py
aws_helper/connection.py
aws_helper/sns.py
aws_helper.egg-info/PKG-INFO
aws_helper.egg-info/SOURCES.txt
aws_helper.egg-info/dependency_links.txt
aws_helper.egg-info/top_level.txt