Metadata-Version: 1.0
Name: aws-helper
Version: 0.2.2
Summary: Helpers for dealing with AWS services.
Home-page: UNKNOWN
Author: Michael Barrett
Author-email: loki77@gmail.com
License: UNKNOWN
Platform: UNKNOWN
